setup.py
vigenerecipher/__init__.py
vigenerecipher.egg-info/PKG-INFO
vigenerecipher.egg-info/SOURCES.txt
vigenerecipher.egg-info/dependency_links.txt
vigenerecipher.egg-info/not-zip-safe
vigenerecipher.egg-info/top_level.txt