Metadata-Version: 1.0
Name: vigenerecipher
Version: 0.2
Summary: The Vigenère cipher is a cryptography method that uses a series of different Caesar numbers based on the letters of a password. This is a simplified version of a more general polyalphabetical substitution figure invented by Leon Battista Alberti about 1465.
Home-page: https://github.com/andersongomes001/vigenerecipher
Author: Anderson Gomes
Author-email: comprasgomes@hotmail.com
License: GNU GPL v3
Platform: UNKNOWN
